{
    "key": "group_667d223f5cb23",
    "title": "CB Side Tab Group (2024)",
    "fields": [
        {
            "key": "field_667d223f65729",
            "label": "CB Side Tab Group (2024)",
            "name": "",
            "aria-label": "",
            "type": "message",
            "instructions": "",
            "required": 0,
            "conditional_logic": 0,
            "wrapper": {
                "width": "",
                "class": "",
                "id": ""
            },
            "message": "",
            "new_lines": "wpautop",
            "esc_html": 0
        },
        {
            "key": "field_667d223f693c4",
            "label": "Title",
            "name": "title",
            "aria-label": "",
            "type": "text",
            "instructions": "",
            "required": 0,
            "conditional_logic": 0,
            "wrapper": {
                "width": "75",
                "class": "",
                "id": ""
            },
            "default_value": "",
            "maxlength": "",
            "placeholder": "",
            "prepend": "",
            "append": ""
        },
        {
            "key": "field_667d37f4123d2",
            "label": "Title Class",
            "name": "title_class",
            "aria-label": "",
            "type": "radio",
            "instructions": "",
            "required": 0,
            "conditional_logic": 0,
            "wrapper": {
                "width": "25",
                "class": "",
                "id": ""
            },
            "choices": {
                "H1": "H1",
                "H2": "H2"
            },
            "default_value": "H2",
            "return_format": "value",
            "allow_null": 0,
            "other_choice": 0,
            "layout": "horizontal",
            "save_other_choice": 0
        },
        {
            "key": "field_667d223f6d034",
            "label": "Intro",
            "name": "intro",
            "aria-label": "",
            "type": "textarea",
            "instructions": "",
            "required": 0,
            "conditional_logic": 0,
            "wrapper": {
                "width": "",
                "class": "",
                "id": ""
            },
            "default_value": "",
            "maxlength": "",
            "rows": 2,
            "placeholder": "",
            "new_lines": ""
        },
        {
            "key": "field_667d223f70d17",
            "label": "Tab 1",
            "name": "",
            "aria-label": "",
            "type": "tab",
            "instructions": "",
            "required": 0,
            "conditional_logic": 0,
            "wrapper": {
                "width": "",
                "class": "",
                "id": ""
            },
            "placement": "top",
            "endpoint": 0,
            "selected": 0
        },
        {
            "key": "field_667d29745988b",
            "label": "Title",
            "name": "tab_1_title",
            "aria-label": "",
            "type": "text",
            "instructions": "",
            "required": 0,
            "conditional_logic": 0,
            "wrapper": {
                "width": "",
                "class": "",
                "id": ""
            },
            "default_value": "",
            "maxlength": "",
            "placeholder": "",
            "prepend": "",
            "append": ""
        },
        {
            "key": "field_667d223f7497b",
            "label": "Content",
            "name": "tab_1_content",
            "aria-label": "",
            "type": "textarea",
            "instructions": "",
            "required": 0,
            "conditional_logic": 0,
            "wrapper": {
                "width": "",
                "class": "",
                "id": ""
            },
            "default_value": "",
            "maxlength": "",
            "rows": 2,
            "placeholder": "",
            "new_lines": ""
        },
        {
            "key": "field_667d223f785e9",
            "label": "Link",
            "name": "tab_1_link",
            "aria-label": "",
            "type": "link",
            "instructions": "",
            "required": 0,
            "conditional_logic": 0,
            "wrapper": {
                "width": "",
                "class": "",
                "id": ""
            },
            "return_format": "array"
        },
        {
            "key": "field_667d2287582c7",
            "label": "Image",
            "name": "tab_1_image",
            "aria-label": "",
            "type": "image",
            "instructions": "",
            "required": 0,
            "conditional_logic": 0,
            "wrapper": {
                "width": "",
                "class": "",
                "id": ""
            },
            "return_format": "id",
            "library": "all",
            "min_width": "",
            "min_height": "",
            "min_size": "",
            "max_width": "",
            "max_height": "",
            "max_size": "",
            "mime_types": "",
            "preview_size": "thumbnail"
        },
        {
            "key": "field_667d223f7c22c",
            "label": "Tab 2",
            "name": "",
            "aria-label": "",
            "type": "tab",
            "instructions": "",
            "required": 0,
            "conditional_logic": 0,
            "wrapper": {
                "width": "",
                "class": "",
                "id": ""
            },
            "placement": "top",
            "endpoint": 0,
            "selected": 0
        },
        {
            "key": "field_667d29835988c",
            "label": "Title",
            "name": "tab_2_title",
            "aria-label": "",
            "type": "text",
            "instructions": "",
            "required": 0,
            "conditional_logic": 0,
            "wrapper": {
                "width": "",
                "class": "",
                "id": ""
            },
            "default_value": "",
            "maxlength": "",
            "placeholder": "",
            "prepend": "",
            "append": ""
        },
        {
            "key": "field_667d223f7fee1",
            "label": "Content",
            "name": "tab_2_content",
            "aria-label": "",
            "type": "textarea",
            "instructions": "",
            "required": 0,
            "conditional_logic": 0,
            "wrapper": {
                "width": "",
                "class": "",
                "id": ""
            },
            "default_value": "",
            "maxlength": "",
            "rows": 2,
            "placeholder": "",
            "new_lines": ""
        },
        {
            "key": "field_667d223f83b8d",
            "label": "Link",
            "name": "tab_2_link",
            "aria-label": "",
            "type": "link",
            "instructions": "",
            "required": 0,
            "conditional_logic": 0,
            "wrapper": {
                "width": "",
                "class": "",
                "id": ""
            },
            "return_format": "array"
        },
        {
            "key": "field_667d22b8582c8",
            "label": "Image",
            "name": "tab_2_image",
            "aria-label": "",
            "type": "image",
            "instructions": "",
            "required": 0,
            "conditional_logic": 0,
            "wrapper": {
                "width": "",
                "class": "",
                "id": ""
            },
            "return_format": "id",
            "library": "all",
            "min_width": "",
            "min_height": "",
            "min_size": "",
            "max_width": "",
            "max_height": "",
            "max_size": "",
            "mime_types": "",
            "preview_size": "thumbnail"
        },
        {
            "key": "field_667d223f877eb",
            "label": "Tab 3",
            "name": "",
            "aria-label": "",
            "type": "tab",
            "instructions": "",
            "required": 0,
            "conditional_logic": 0,
            "wrapper": {
                "width": "",
                "class": "",
                "id": ""
            },
            "placement": "top",
            "endpoint": 0,
            "selected": 0
        },
        {
            "key": "field_667d298f5988d",
            "label": "Title",
            "name": "tab_3_title",
            "aria-label": "",
            "type": "text",
            "instructions": "",
            "required": 0,
            "conditional_logic": 0,
            "wrapper": {
                "width": "",
                "class": "",
                "id": ""
            },
            "default_value": "",
            "maxlength": "",
            "placeholder": "",
            "prepend": "",
            "append": ""
        },
        {
            "key": "field_667d223f8b45d",
            "label": "Content",
            "name": "tab_3_content",
            "aria-label": "",
            "type": "textarea",
            "instructions": "",
            "required": 0,
            "conditional_logic": 0,
            "wrapper": {
                "width": "",
                "class": "",
                "id": ""
            },
            "default_value": "",
            "maxlength": "",
            "rows": 2,
            "placeholder": "",
            "new_lines": ""
        },
        {
            "key": "field_667d223f8f0fd",
            "label": "Link",
            "name": "tab_3_link",
            "aria-label": "",
            "type": "link",
            "instructions": "",
            "required": 0,
            "conditional_logic": 0,
            "wrapper": {
                "width": "",
                "class": "",
                "id": ""
            },
            "return_format": "array"
        },
        {
            "key": "field_667d22dd582c9",
            "label": "Image",
            "name": "tab_3_image",
            "aria-label": "",
            "type": "image",
            "instructions": "",
            "required": 0,
            "conditional_logic": 0,
            "wrapper": {
                "width": "",
                "class": "",
                "id": ""
            },
            "return_format": "id",
            "library": "all",
            "min_width": "",
            "min_height": "",
            "min_size": "",
            "max_width": "",
            "max_height": "",
            "max_size": "",
            "mime_types": "",
            "preview_size": "thumbnail"
        },
        {
            "key": "field_6810f33d5c547",
            "label": "Tab 4 (Optional)",
            "name": "",
            "aria-label": "",
            "type": "tab",
            "instructions": "",
            "required": 0,
            "conditional_logic": 0,
            "wrapper": {
                "width": "",
                "class": "",
                "id": ""
            },
            "placement": "top",
            "endpoint": 0,
            "selected": 0
        },
        {
            "key": "field_6810f34d5c548",
            "label": "Title",
            "name": "tab_4_title",
            "aria-label": "",
            "type": "text",
            "instructions": "",
            "required": 0,
            "conditional_logic": 0,
            "wrapper": {
                "width": "",
                "class": "",
                "id": ""
            },
            "default_value": "",
            "maxlength": "",
            "allow_in_bindings": 0,
            "placeholder": "",
            "prepend": "",
            "append": ""
        },
        {
            "key": "field_6810f35a5c549",
            "label": "Content",
            "name": "tab_4_content",
            "aria-label": "",
            "type": "textarea",
            "instructions": "",
            "required": 0,
            "conditional_logic": 0,
            "wrapper": {
                "width": "",
                "class": "",
                "id": ""
            },
            "default_value": "",
            "maxlength": "",
            "allow_in_bindings": 1,
            "rows": 2,
            "placeholder": "",
            "new_lines": ""
        },
        {
            "key": "field_6810f36a5c54a",
            "label": "Link",
            "name": "tab_4_link",
            "aria-label": "",
            "type": "link",
            "instructions": "",
            "required": 0,
            "conditional_logic": 0,
            "wrapper": {
                "width": "",
                "class": "",
                "id": ""
            },
            "return_format": "array",
            "allow_in_bindings": 1
        },
        {
            "key": "field_6810f3785c54b",
            "label": "Image",
            "name": "tab_4_image",
            "aria-label": "",
            "type": "image",
            "instructions": "",
            "required": 0,
            "conditional_logic": 0,
            "wrapper": {
                "width": "",
                "class": "",
                "id": ""
            },
            "return_format": "id",
            "library": "all",
            "min_width": "",
            "min_height": "",
            "min_size": "",
            "max_width": "",
            "max_height": "",
            "max_size": "",
            "mime_types": "",
            "allow_in_bindings": 1,
            "preview_size": "thumbnail"
        }
    ],
    "location": [
        [
            {
                "param": "block",
                "operator": "==",
                "value": "acf\/cb-side-tab-group-2024"
            }
        ]
    ],
    "menu_order": 0,
    "position": "normal",
    "style": "default",
    "label_placement": "top",
    "instruction_placement": "label",
    "hide_on_screen": "",
    "active": true,
    "description": "",
    "show_in_rest": 0
}